sekvo/__about__.py
sekvo/__init__.py
sekvo/start.sh
sekvo/cli/__init__.py
sekvo/cli/main.py
sekvo/cli/plugin.py
sekvo/config/README.md
sekvo/config/__init__.py
sekvo/config/base.py
sekvo/config/provider_config.py
sekvo/config/settings.py
sekvo/config/types.py
sekvo/core/__init__.py
sekvo/core/exceptions.py
sekvo/core/prompt_pipe.py
sekvo/core/types.py
sekvo/providers/__init__.py
sekvo/providers/base.py
sekvo/providers/simplemind_adapter.py
sekvo/providers/anthropic/__init__.py
sekvo/providers/anthropic/generate.py
sekvo-0.1.1.dist-info/METADATA
sekvo-0.1.1.dist-info/WHEEL
sekvo-0.1.1.dist-info/entry_points.txt
sekvo-0.1.1.dist-info/licenses/LICENSE
sekvo-0.1.1.dist-info/RECORD
