Metadata-Version: 2.4
Name: sekvo
Version: 0.1.1
Summary: Your project description
License-File: LICENSE
Requires-Python: >=3.13
Requires-Dist: anthropic>=0.49.0
Requires-Dist: click
Requires-Dist: pip==24.2
Requires-Dist: pydantic-settings
Requires-Dist: pydantic>=2.0.0
Requires-Dist: pyproject-freeze==0.1.1
Requires-Dist: rich
Requires-Dist: simplemind>=0.3.3
Requires-Dist: tomlkit==0.13.2
Provides-Extra: all
Requires-Dist: anthropic>=0.18.0; extra == 'all'
Requires-Dist: google-cloud-aiplatform>=1.40.0; extra == 'all'
Requires-Dist: openai>=1.12.0; extra == 'all'
Provides-Extra: anthropic
Requires-Dist: anthropic>=0.18.0; extra == 'anthropic'
Provides-Extra: dev
Requires-Dist: mypy>=1.8.0; extra == 'dev'
Requires-Dist: pytest-asyncio>=0.23.0; extra == 'dev'
Requires-Dist: pytest-cov>=4.1.0; extra == 'dev'
Requires-Dist: pytest>=8.0.0; extra == 'dev'
Requires-Dist: ruff>=0.3.0; extra == 'dev'
Provides-Extra: openai
Requires-Dist: openai>=1.12.0; extra == 'openai'
Provides-Extra: vertexai
Requires-Dist: google-cloud-aiplatform>=1.40.0; extra == 'vertexai'
